sneakpeek/api.py
sneakpeek/logging.py
sneakpeek/metrics.py
sneakpeek/middleware/base.py
sneakpeek/middleware/parser.py
sneakpeek/middleware/proxy_middleware.py
sneakpeek/middleware/rate_limiter_middleware.py
sneakpeek/middleware/requests_logging_middleware.py
sneakpeek/middleware/robots_txt_middleware.py
sneakpeek/middleware/user_agent_injecter_middleware.py
sneakpeek/queue/consumer.py
sneakpeek/queue/in_memory_storage.py
sneakpeek/queue/model.py
sneakpeek/queue/queue.py
sneakpeek/queue/redis_storage.py
sneakpeek/queue/tasks.py
sneakpeek/queue/tests/test_consumer.py
sneakpeek/queue/tests/test_queue.py
sneakpeek/queue/tests/test_queue_storage.py
sneakpeek/scheduler/in_memory_lease_storage.py
sneakpeek/scheduler/model.py
sneakpeek/scheduler/redis_lease_storage.py
sneakpeek/scheduler/scheduler.py
sneakpeek/scheduler/tests/test_lease_storage.py
sneakpeek/scraper/context.py
sneakpeek/scraper/dynamic_scraper_handler.py
sneakpeek/scraper/ephemeral_scraper_task_handler.py
sneakpeek/scraper/in_memory_storage.py
sneakpeek/scraper/model.py
sneakpeek/scraper/redis_storage.py
sneakpeek/scraper/runner.py
sneakpeek/scraper/task_handler.py
sneakpeek/scraper/tests/test_context.py
sneakpeek/scraper/tests/test_dynamic_scraper_handler.py
sneakpeek/scraper/tests/test_scraper_storage.py
sneakpeek/server.py
sneakpeek/session_loggers/base.py
sneakpeek/session_loggers/file_logger.py
sneakpeek/session_loggers/redis_logger.py
sneakpeek/static/.gitkeep
sneakpeek/static/docs/.buildinfo
sneakpeek/static/docs/.doctrees/api.doctree
sneakpeek/static/docs/.doctrees/deployment.doctree
sneakpeek/static/docs/.doctrees/design.doctree
sneakpeek/static/docs/.doctrees/environment.pickle
sneakpeek/static/docs/.doctrees/index.doctree
sneakpeek/static/docs/.doctrees/local_debugging.doctree
sneakpeek/static/docs/.doctrees/middleware/index.doctree
sneakpeek/static/docs/.doctrees/middleware/new_middleware.doctree
sneakpeek/static/docs/.doctrees/middleware/proxy_middleware.doctree
sneakpeek_py-0.2.2.dist-info/METADATA
sneakpeek_py-0.2.2.dist-info/WHEEL
sneakpeek_py-0.2.2.dist-info/RECORD
