Metadata-Version: 2.1
Name: sneakpeek-py
Version: 0.2.2
Summary: Sneakpeek is a framework that helps to quickly and conviniently develop scrapers. It's the best choice for scrapers that have some specific complex scraping logic that needs to be run on a constant basis.
Home-page: https://github.com/flulemon/sneakpeek
License: BSD-3-Clause
Author: Dan Yazovsky
Author-email: daniil.yazovsky@gmail.com
Maintainer: Dan Yazovsky
Maintainer-email: daniil.yazovsky@gmail.com
Requires-Python: >=3.10,<4.0
Classifier: Development Status :: 2 - Pre-Alpha
Classifier: Framework :: FastAPI
Classifier: Framework :: Pydantic
Classifier: Intended Audience :: Developers
Classifier: License :: OSI Approved :: BSD License
Classifier: Operating System :: OS Independent
Classifier: Programming Language :: Python
Classifier: Programming Language :: Python :: 3
Classifier: Programming Language :: Python :: 3.10
Classifier: Programming Language :: Python :: 3.11
Classifier: Programming Language :: Python :: 3
Classifier: Programming Language :: Python :: 3.10
Classifier: Programming Language :: Python :: 3.11
Classifier: Programming Language :: Python :: 3.12
Classifier: Topic :: Internet :: WWW/HTTP :: Indexing/Search
Classifier: Topic :: Software Development :: Libraries :: Application Frameworks
Provides-Extra: docs
Requires-Dist: Sphinx (==4.2.0) ; extra == "docs"
Requires-Dist: aiohttp (>=3.8.4,<4.0.0)
Requires-Dist: apscheduler (>=3.10.1,<4.0.0)
Requires-Dist: cachetools (>=5.3.0,<6.0.0)
Requires-Dist: fake-useragent (>=1.1.3,<2.0.0)
Requires-Dist: fastapi (>=0.95.0,<0.96.0)
Requires-Dist: fastapi-jsonrpc (>=2.4.1,<3.0.0)
Requires-Dist: prometheus-client (>=0.16.0,<0.17.0)
Requires-Dist: pydantic (>=1.10.7,<2.0.0)
Requires-Dist: redis (>=4.5.4,<5.0.0)
Requires-Dist: sphinx-rtd-theme (==1.0.0) ; extra == "docs"
Requires-Dist: sphinxcontrib-napoleon (==0.7) ; extra == "docs"
Requires-Dist: uvicorn (>=0.21.1,<0.22.0)
Requires-Dist: yarl (>=1.9.1,<2.0.0)
Project-URL: Documentation, https://sneakpeek-py.readthedocs.io/en/latest/
Project-URL: Repository, https://github.com/flulemon/sneakpeek
